{
  "version": 1,
  "skills": {
    "brainstorming": {
      "source": "obra/superpowers",
      "sourceType": "github",
      "skillPath": "skills/brainstorming/SKILL.md",
      "computedHash": "0c877c8521ec97a5d55fa682d33122b811aebddd4788b92ac008efe85cd305cd"
    },
    "caveman": {
      "source": "juliusbrussee/caveman",
      "sourceType": "github",
      "skillPath": "skills/caveman/SKILL.md",
      "computedHash": "b0e7741886c0c32270cedc1a2fc21c2879d90964d3ce00f24952de7064613404"
    }
  }
}
